langchain_ibm-1.0.2.dist-info/METADATA
langchain_ibm-1.0.2.dist-info/WHEEL
langchain_ibm-1.0.2.dist-info/entry_points.txt
langchain_ibm-1.0.2.dist-info/licenses/LICENSE
langchain_ibm/__init__.py
langchain_ibm/agent_toolkits/__init__.py
langchain_ibm/agent_toolkits/sql/__init__.py
langchain_ibm/agent_toolkits/sql/tool.py
langchain_ibm/agent_toolkits/sql/toolkit.py
langchain_ibm/agent_toolkits/utility/__init__.py
langchain_ibm/agent_toolkits/utility/toolkit.py
langchain_ibm/agent_toolkits/utility/utils.py
langchain_ibm/chat_models.py
langchain_ibm/embeddings.py
langchain_ibm/llms.py
langchain_ibm/py.typed
langchain_ibm/rerank.py
langchain_ibm/utilities/__init__.py
langchain_ibm/utilities/sql_database.py
langchain_ibm/utils.py
langchain_ibm-1.0.2.dist-info/RECORD
