Metadata-Version: 2.1
Name: langchain-ibm
Version: 1.0.2
Summary: An integration package connecting IBM watsonx.ai and LangChain
Author: IBM
License: MIT
Project-URL: Source Code, https://github.com/langchain-ai/langchain-ibm/tree/main/libs/ibm
Project-URL: repository, https://github.com/langchain-ai/langchain-ibm
Requires-Python: <3.14,>=3.10
Requires-Dist: langchain-core<2.0.0,>=1.0.0
Requires-Dist: ibm-watsonx-ai<2.0.0,>=1.3.37
Provides-Extra: sql-toolkit
Requires-Dist: pyarrow>=3.0.0; extra == "sql-toolkit"
